MANIFEST.in
README.rst
buildout.cfg
py3.cfg
setup.py
docs/CHANGES.rst
docs/LICENSE
src/croniter/__init__.py
src/croniter/croniter.py
src/croniter.egg-info/PKG-INFO
src/croniter.egg-info/SOURCES.txt
src/croniter.egg-info/dependency_links.txt
src/croniter.egg-info/requires.txt
src/croniter.egg-info/top_level.txt
src/croniter/tests/__init__.py
src/croniter/tests/base.py
src/croniter/tests/test_croniter.py
src/croniter/tests/test_speed.py
src/croniter_hpx.egg-info/PKG-INFO
src/croniter_hpx.egg-info/SOURCES.txt
src/croniter_hpx.egg-info/dependency_links.txt
src/croniter_hpx.egg-info/requires.txt
src/croniter_hpx.egg-info/top_level.txt