Metadata-Version: 1.1
Name: croniter-hpx
Version: 0.3.12.dev0
Summary: croniter provides iteration for datetime object with cron like format
Home-page: http://github.com/kiorky/croniter
Author: Matsumoto Taichi, kiorky
Author-email: taichino@gmail.com, kiorky@cryptelium.net
License: MIT License
Keywords: datetime,iterator,cron
Platform: UNKNOWN
Classifier: Development Status :: 4 - Beta
Classifier: Intended Audience :: Developers
Classifier: License :: OSI Approved :: MIT License
Classifier: Operating System :: POSIX
Classifier: Programming Language :: Python
Classifier: Topic :: Software Development :: Libraries :: Python Modules
